setup.py
Catkins_Dream/Catkins_Dream.py
Catkins_Dream/__init__.py
Catkins_Dream/out_interface.py
Catkins_Dream/tempCodeRunnerFile.py
Catkins_Dream.egg-info/PKG-INFO
Catkins_Dream.egg-info/SOURCES.txt
Catkins_Dream.egg-info/dependency_links.txt
Catkins_Dream.egg-info/entry_points.txt
Catkins_Dream.egg-info/top_level.txt