Metadata-Version: 1.1
Name: Catkins-Dream
Version: 0.0.1
Summary: 任生命烟花般绽放于夜空，似絮梦留过人间。旭日，东升
Home-page: https://blog.csdn.net/qq_43071318/article/details/109384574?spm=1001.2014.3001.5501
Author: 徐嘉志
Author-email: X_jaguar@163.com
License: UNKNOWN
Platform: UNKNOWN
Classifier: Programming Language :: Python :: 3
Classifier: License :: OSI Approved :: MIT License
Classifier: Operating System :: OS Independent
